{"йўңж–Үеӯ—":{"type":"emoticon","container":[{"icon":"OПүO","text":"Author: DIYgod"},{"icon":"|Вҙгғ»Пүгғ»)гғҺ","text":"Hi"},{"icon":"гғҫ(вү§вҲҮвүҰ*)гӮқ","text":"ејҖеҝғ"},{"icon":"(вҳҶПүвҳҶ)","text":"жҳҹжҳҹзңј"},{"icon":"пјҲв•ҜвҖөв–ЎвҖІпјүв•Ҝпёөв”ҙв”Җв”ҙ","text":"жҺҖжЎҢ"},{"icon":"пҝЈп№ғпҝЈ","text":"жөҒеҸЈж°ҙ"},{"icon":"(/Пүпјј)","text":"жҚӮи„ё"},{"icon":"вҲ ( бҗӣ гҖҚвҲ )пјҝ","text":"з»ҷи·Ә"},{"icon":"(а№‘вҖўМҖг…ҒвҖўМҒаё…)","text":"Hi"},{"icon":"вҶ’_вҶ’","text":"ж–ңзңј"},{"icon":"аӯ§(а№‘вҖўМҖвҢ„вҖўМҒа№‘)а«ӯ","text":"еҠ жІ№"},{"icon":"Щ©(ЛҠб—ңЛӢ*)ЩҲ","text":"жңүжңЁжңүWiFi"},{"icon":"(гғҺВ°ОҝВ°)гғҺ","text":"еүҚж–№й«ҳиғҪйў„иӯҰ"},{"icon":"(Вҙа®Үзҡҝа®ҮпҪҖ)","text":"жҲ‘д»ҺжңӘи§ҒиҝҮеҰӮжӯӨеҺҡйўңж— иҖ»д№Ӣдәә"},{"icon":"вҢҮв—Ҹп№Ҹв—ҸвҢҮ","text":"еҗ“жӯ»е®қе®қжғ№"},{"icon":"(аё…ВҙПү`аё…)","text":"е·Ійҳ…з•ҷзҲӘ"},{"icon":"(в•ҜВ°AВ°)в•Ҝпёөв—Ӣв—Ӣв—Ӣ","text":"еҺ»еҗ§еӨ§еёҲзҗғ"},{"icon":"ПҶ(пҝЈвҲҮпҝЈo)","text":"еӨӘиҗҢжғ№"},{"icon":"гғҫ(ВҙпҪҘ пҪҘпҪҖпҪЎ)гғҺ\"","text":"е’Ұе’Ұе’Ұ"},{"icon":"( аёҮ бө’МҢзҡҝбө’МҢ)аёҮвҒјВівӮҢвӮғ","text":"ж°”е‘је‘ј"},{"icon":"(Гіп№ҸГІпҪЎ)","text":"жҲ‘еҸ—еҲ°дәҶжғҠеҗ“"},{"icon":"ОЈ(гҒЈ В°Р” В°;)гҒЈ","text":"д»Җд№Ҳй¬ј"},{"icon":"( ,,ВҙпҪҘПүпҪҘ)пҫү\"(ВҙгҒЈПүпҪҘпҪҖпҪЎ)","text":"ж‘ёж‘ёеӨҙ"},{"icon":"в•®(в•Ҝв–Ҫв•°)в•ӯ ","text":"ж— еҘҲ"},{"icon":"o(*////в–Ҫ////*)q ","text":"и„ёзәў"},{"icon":"пјһп№Ҹпјң","text":""},{"icon":"( а№‘ВҙвҖўПүвҖў) \"(гҶҶбҙ—гҶҶ)","text":""}]},"Emoji":{"type":"emoji","container":[{"icon":"рҹҳӮ","text":""},{"icon":"рҹҳҖ","text":""},{"icon":"рҹҳ…","text":""},{"icon":"рҹҳҠ","text":""},{"icon":"рҹҷӮ","text":""},{"icon":"рҹҷғ","text":""},{"icon":"рҹҳҢ","text":""},{"icon":"рҹҳҚ","text":""},{"icon":"рҹҳҳ ","text":""},{"icon":"рҹҳң","text":""},{"icon":"рҹҳқ","text":""},{"icon":"рҹҳҸ","text":""},{"icon":"рҹҳ’","text":""},{"icon":"рҹҷ„","text":""},{"icon":"рҹҳі ","text":""},{"icon":"рҹҳЎ","text":""},{"icon":"рҹҳ”","text":""},{"icon":"рҹҳ«","text":""},{"icon":"рҹҳұ","text":""},{"icon":"рҹҳӯ","text":""},{"icon":"рҹ’©","text":""},{"icon":"рҹ‘»","text":""},{"icon":"рҹҷҢ","text":""},{"icon":"рҹ–•","text":""},{"icon":"рҹ‘Қ","text":""},{"icon":"рҹ‘«","text":""},{"icon":"рҹ‘¬","text":""},{"icon":"рҹ‘ӯ","text":""},{"icon":"рҹҢҡ","text":""},{"icon":"рҹҢқ","text":""},{"icon":"рҹҷҲ","text":""},{"icon":"рҹ’Ҡ","text":""},{"icon":"рҹҳ¶","text":""},{"icon":"рҹҷҸ","text":""},{"icon":"рҹҚҰ","text":""},{"icon":"рҹҚү","text":""},{"icon":"рҹҳЈ","text":""}]},"Bilibili":{"type":"image","container":[{"icon":"<img src=\"https://cdn.jsdelivr.net/gh/2x-ercha/twikoo-magic@master/image/bilibili2233/1.png\" onerror='this.onerror=null;this.src="/img/404.jpg"'>","text":"tv_doge"},{"icon":"<img src=\"https://cdn.jsdelivr.net/gh/2x-ercha/twikoo-magic@master/image/bilibili2233/10.png\" onerror='this.onerror=null;this.src="/img/404.jpg"'>","text":"tv_дәІдәІ"},{"icon":"<img src=\"https://owo.imaegoo.com/bilibili/bb690d4107620f1c15cff29509db529a73aee261.png\" onerror='this.onerror=null;this.src="/img/404.jpg"'>","text":"tv_еҒ·з¬‘"},{"icon":"<img src=\"https://owo.imaegoo.com/bilibili/180129b8ea851044ce71caf55cc8ce44bd4a4fc8.png\" onerror='this.onerror=null;this.src="/img/404.jpg"'>","text":"tv_еҶҚи§Ғ"},{"icon":"<img src=\"https://owo.imaegoo.com/bilibili/b9cbc755c2b3ee43be07ca13de84e5b699a3f101.png\" onerror='this.onerror=null;this.src="/img/404.jpg"'>","text":"tv_еҶ·жј "},{"icon":"<img src=\"https://owo.imaegoo.com/bilibili/34ba3cd204d5b05fec70ce08fa9fa0dd612409ff.png\" onerror='this.onerror=null;this.src="/img/404.jpg"'>","text":"tv_еҸ‘жҖ’"},{"icon":"<img src=\"https://owo.imaegoo.com/bilibili/34db290afd2963723c6eb3c4560667db7253a21a.png\" onerror='this.onerror=null;this.src="/img/404.jpg"'>","text":"tv_еҸ‘иҙў"},{"icon":"<img src=\"https://owo.imaegoo.com/bilibili/9e55fd9b500ac4b96613539f1ce2f9499e314ed9.png\" onerror='this.onerror=null;this.src="/img/404.jpg"'>","text":"tv_еҸҜзҲұ"},{"icon":"<img src=\"https://owo.imaegoo.com/bilibili/09dd16a7aa59b77baa1155d47484409624470c77.png\" onerror='this.onerror=null;this.src="/img/404.jpg"'>","text":"tv_еҗҗиЎҖ"},{"icon":"<img src=\"https://owo.imaegoo.com/bilibili/fe1179ebaa191569b0d31cecafe7a2cd1c951c9d.png\" onerror='this.onerror=null;this.src="/img/404.jpg"'>","text":"tv_е‘Ҷ"},{"icon":"<img src=\"https://owo.imaegoo.com/bilibili/9f996894a39e282ccf5e66856af49483f81870f3.png\" onerror='this.onerror=null;this.src="/img/404.jpg"'>","text":"tv_е‘•еҗҗ"},{"icon":"<img src=\"https://owo.imaegoo.com/bilibili/241ee304e44c0af029adceb294399391e4737ef2.png\" onerror='this.onerror=null;this.src="/img/404.jpg"'>","text":"tv_еӣ°"},{"icon":"<img src=\"https://owo.imaegoo.com/bilibili/1f0b87f731a671079842116e0991c91c2c88645a.png\" onerror='this.onerror=null;this.src="/img/404.jpg"'>","text":"tv_еқҸз¬‘"},{"icon":"<img src=\"https://owo.imaegoo.com/bilibili/093c1e2c490161aca397afc45573c877cdead616.png\" onerror='this.onerror=null;this.src="/img/404.jpg"'>","text":"tv_еӨ§дҪ¬"},{"icon":"<img src=\"https://owo.imaegoo.com/bilibili/23269aeb35f99daee28dda129676f6e9ea87934f.png\" onerror='this.onerror=null;this.src="/img/404.jpg"'>","text":"tv_еӨ§е“ӯ"},{"icon":"<img src=\"https://owo.imaegoo.com/bilibili/d04dba7b5465779e9755d2ab6f0a897b9b33bb77.png\" onerror='this.onerror=null;this.src="/img/404.jpg"'>","text":"tv_е§”еұҲ"},{"icon":"<img src=\"https://owo.imaegoo.com/bilibili/a37683fb5642fa3ddfc7f4e5525fd13e42a2bdb1.png\" onerror='this.onerror=null;this.src="/img/404.jpg"'>","text":"tv_е®ізҫһ"},{"icon":"<img src=\"https://owo.imaegoo.com/bilibili/7cfa62dafc59798a3d3fb262d421eeeff166cfa4.png\" onerror='this.onerror=null;this.src="/img/404.jpg"'>","text":"tv_е°ҙе°¬"},{"icon":"<img src=\"https://owo.imaegoo.com/bilibili/70dc5c7b56f93eb61bddba11e28fb1d18fddcd4c.png\" onerror='this.onerror=null;this.src="/img/404.jpg"'>","text":"tv_еҫ®з¬‘"},{"icon":"<img src=\"https://owo.imaegoo.com/bilibili/90cf159733e558137ed20aa04d09964436f618a1.png\" onerror='this.onerror=null;this.src="/img/404.jpg"'>","text":"tv_жҖқиҖғ"},{"icon":"<img src=\"https://owo.imaegoo.com/bilibili/0d15c7e2ee58e935adc6a7193ee042388adc22af.png\" onerror='this.onerror=null;this.src="/img/404.jpg"'>","text":"tv_жғҠеҗ“"}]}}